{
    "test_cases": [
        {
            "setup": [
                {
                    "Margin": {
                        "CPU_PLL": 3050,
                        "PCP_VRM": -50,
                        "RCA_VRM": 0,
                        "SOC_VRM": 40
                    },
                    "NVPARAM": {
                        "NvParameters": {
                            "0x1F0020": "0xffff",
                            "0xe34000": "0xFFFFFFC4",
                            "0x1F0088": "0x02020003",
                            "0x1F0090": "0x02020003",
                            "0x1F0098": "0x02020003",
                            "0x1F00A0": "0x02020003",
                            "0x1F00A8": "0x00020002",
                            "0x1F00B0": "0x00020002",
                            "0x1F00B8": "0x00020002",
                            "0x1F00C0": "0x00020002",
                            "0x1F00C8": "0x00020002",
                            "0x1F00D0": "0x00020002",
                            "0x1F00D8": "0x00020002",
                            "0x1F00E0": "0x00020002"
                        }
                    }
                }
            ],
            "name": "CentOSTest", "display": "CentOS_v3.1", "config": "test_configs/case_centos_v3.json"
        }
    ]
}
